chop/__init__.py
chop/cli.py
chop/actions/__init__.py
chop/actions/accelerate_peft.py
chop/actions/accelerate_train.py
chop/actions/test.py
chop/actions/train.py
chop/actions/transform.py
chop/actions/validate.py
chop/actions/search/__init__.py
chop/actions/search/search.py
chop/actions/search/search_space/__init__.py
chop/actions/search/search_space/base.py
chop/actions/search/search_space/utils.py
chop/actions/search/search_space/quantization/__init__.py
chop/actions/search/search_space/quantization/graph.py
chop/actions/search/search_space/quantization/manual_hf_module.py
chop/actions/search/strategies/__init__.py
chop/actions/search/strategies/base.py
chop/actions/search/strategies/optuna.py
chop/actions/search/strategies/rl/__init__.py
chop/actions/search/strategies/rl/core_algorithm.py
chop/actions/search/strategies/rl/env.py
chop/actions/search/strategies/runners/__init__.py
chop/actions/search/strategies/runners/hardware/__init__.py
chop/actions/search/strategies/runners/hardware/base.py
chop/actions/search/strategies/runners/hardware/dummy.py
chop/actions/search/strategies/runners/hardware/memory/__init__.py
chop/actions/search/strategies/runners/hardware/memory/avg_bitwidth.py
chop/actions/search/strategies/runners/hardware/memory/model_profiler.py
chop/actions/search/strategies/runners/software/__init__.py
chop/actions/search/strategies/runners/software/base.py
chop/actions/search/strategies/runners/software/eval.py
chop/actions/search/strategies/runners/software/train.py
chop/dataset/__init__.py
chop/dataset/toy_dataset.py
chop/dataset/utils.py
chop/dataset/nerf/__init__.py
chop/dataset/nerf/blender.py
chop/dataset/nerf/ray_utils.py
chop/dataset/nlp/__init__.py
chop/dataset/nlp/language_modeling.py
chop/dataset/nlp/sentiment_analysis.py
chop/dataset/nlp/text_entailment.py
chop/dataset/nlp/translation.py
chop/dataset/physical/__init__.py
chop/dataset/physical/jsc.py
chop/dataset/vision/__init__.py
chop/dataset/vision/cifar.py
mase_tools-1.0.0.dist-info/LICENSE
mase_tools-1.0.0.dist-info/METADATA
mase_tools-1.0.0.dist-info/WHEEL
mase_tools-1.0.0.dist-info/top_level.txt
mase_tools-1.0.0.dist-info/RECORD
